cz_cz_ai.py
cz_ai-0.8.2.dist-info/METADATA
cz_ai-0.8.2.dist-info/WHEEL
cz_ai-0.8.2.dist-info/entry_points.txt
cz_ai-0.8.2.dist-info/top_level.txt
cz_ai-0.8.2.dist-info/RECORD
