Metadata-Version: 2.4
Name: cz_ai
Version: 0.8.2
Summary: A Commitizen plugin that leverages OpenAI's models to automatically generate clear, concise, and conventional commit messages based on your staged git changes.
License: Copyright 2025
Project-URL: Homepage, https://github.com/watadarkstar/cz_ai
Project-URL: Source, https://github.com/watadarkstar/cz_ai
Project-URL: Issue Tracker, https://github.com/watadarkstar/cz_ai/issues
Project-URL: Repository, https://github.com/watadarkstar/cz_ai
Requires-Python: >=3.7
Requires-Dist: commitizen
